no_dm_discord/__init__.py
no_dm_discord/main.py
tests/__init__.py
tests/test_main.py
no_dm_discord-0.1.0.dist-info/LICENSE
no_dm_discord-0.1.0.dist-info/METADATA
no_dm_discord-0.1.0.dist-info/WHEEL
no_dm_discord-0.1.0.dist-info/top_level.txt
no_dm_discord-0.1.0.dist-info/RECORD
