Metadata-Version: 2.1
Name: no-dm-discord
Version: 0.1.0
Summary: A Discord bot that ensures DMs are always turned off in your Discord
Home-page: https://github.com/wbnns/disable-dm-discord-guild
Author: wbnns
Author-email: hello@wbnns.com
Classifier: Programming Language :: Python :: 3
Classifier: License :: OSI Approved :: MIT License
Classifier: Operating System :: OS Independent
Requires-Python: >=3.6
License-File: LICENSE
Requires-Dist: requests
Requires-Dist: python-dotenv
